README.txt
setup.py
bin/pluckr
pluckr/__init__.py
pluckr/core.py
pluckr/helpers.py
pluckr.egg-info/PKG-INFO
pluckr.egg-info/SOURCES.txt
pluckr.egg-info/dependency_links.txt
pluckr.egg-info/pbr.json
pluckr.egg-info/top_level.txt