Metadata-Version: 1.0
Name: pluckr
Version: 0.0.9
Summary: Pluck columns from CSV files in the command line. Like cut or awk, but doesn't choke on delimiter escaping.
Home-page: https://github.com/philadams/pluckr
Author: Phil Adams
Author-email: philadams.net@gmail.com
License: LICENSE.txt
Platform: UNKNOWN
